{
  "schemaVersion": 18,
  "id": "recette-per142-bouclier-r3-petit-bouclier",
  "name": "Recette PER-142 — Défense au bouclier (rang 3) avec petit bouclier",
  "identity": {
    "description": "ATTENDU : Défense au bouclier au rang 3 → +1 DEF (pas encore +2, réservé au rang 5) et RD de 3 contre les attaques de zone. Petit bouclier porté (DEF +1 mondaine). DEF = 12 (base) + 1 (bouclier mondain) + 1 (capacité) = 14."
  },
  "campaignId": null,
  "playerId": null,
  "status": "active",
  "ancestryId": "humain",
  "classId": "guerrier",
  "level": 5,
  "priestVocation": null,
  "portraitVariant": "default",
  "firearmsAllowed": true,
  "abilities": {
    "FOR": 3,
    "AGI": 2,
    "CON": 2,
    "PER": 1,
    "CHA": 0,
    "INT": -1,
    "VOL": 0
  },
  "baseAbilities": {
    "FOR": 3,
    "AGI": 2,
    "CON": 2,
    "PER": 1,
    "CHA": 0,
    "INT": -1,
    "VOL": 0
  },
  "ancestryChoices": [],
  "ancestryPathId": "humain",
  "featureIds": [
    "bouclier-r3"
  ],
  "featureChoices": {},
  "effectToggles": {},
  "effectInputs": {},
  "usageCounters": {},
  "depletion": {},
  "purse": {
    "platinum": 0,
    "gold": 0,
    "silver": 0,
    "copper": 0
  },
  "levelUpHistory": [],
  "equipment": [
    {
      "itemId": "petit-bouclier",
      "quantity": 1,
      "worn": {
        "slot": "shield"
      }
    }
  ],
  "overrides": {},
  "notes": "PER-142 — rang 3 : +1 DEF et RD zone 3.",
  "createdAt": "2026-01-01T00:00:00.000Z",
  "updatedAt": "2026-01-01T00:00:00.000Z"
}
